Metadata-Version: 1.1
Name: kalikl
Version: 0.0.3
Summary: A very basic calculator
Home-page: UNKNOWN
Author: Brandon Bullock
Author-email: NoTDistorted@gmail.com
License: MIT
Keywords: language
Platform: UNKNOWN
Classifier: Development Status :: 5 - Production/Stable
Classifier: Intended Audience :: Education
Classifier: Operating System :: Microsoft :: Windows :: Windows 10
Classifier: License :: OSI Approved :: MIT License
Classifier: Programming Language :: Python :: 3
